runtm_cli/__init__.py
runtm_cli/api_client.py
runtm_cli/auth.py
runtm_cli/config.py
runtm_cli/main.py
runtm_cli/telemetry.py
runtm_cli/commands/__init__.py
runtm_cli/commands/admin.py
runtm_cli/commands/approve.py
runtm_cli/commands/deploy.py
runtm_cli/commands/destroy.py
runtm_cli/commands/domain.py
runtm_cli/commands/fix.py
runtm_cli/commands/init.py
runtm_cli/commands/list.py
runtm_cli/commands/logs.py
runtm_cli/commands/run.py
runtm_cli/commands/search.py
runtm_cli/commands/secrets.py
runtm_cli/commands/session.py
runtm_cli/commands/status.py
runtm_cli/commands/validate.py
runtm-0.2.11.dist-info/METADATA
runtm-0.2.11.dist-info/WHEEL
runtm-0.2.11.dist-info/entry_points.txt
runtm-0.2.11.dist-info/licenses/LICENSE
runtm-0.2.11.dist-info/RECORD
