Metadata-Version: 2.4
Name: runtm
Version: 0.2.11
Summary: Sandboxes where AI agents build and deploy. Spin up isolated environments for Claude Code, Cursor, and other agents.
Project-URL: Homepage, https://runtm.com
Project-URL: Documentation, https://docs.runtm.com
Project-URL: Repository, https://github.com/runtm-ai/runtm
Project-URL: Issues, https://github.com/runtm-ai/runtm/issues
Author-email: Gustavo Trigos <gus@runtm.com>
Maintainer-email: Gustavo Trigos <gus@runtm.com>
License: Apache-2.0
License-File: LICENSE
Keywords: ai,cli,deployment,devops,fly.io,serverless
Classifier: Development Status :: 4 - Beta
Classifier: Environment :: Console
Classifier: Intended Audience :: Developers
Classifier: License :: OSI Approved :: Apache Software License
Classifier: Operating System :: OS Independent
Classifier: Programming Language :: Python :: 3
Classifier: Programming Language :: Python :: 3.9
Classifier: Programming Language :: Python :: 3.10
Classifier: Programming Language :: Python :: 3.11
Classifier: Programming Language :: Python :: 3.12
Classifier: Topic :: Software Development :: Build Tools
Classifier: Topic :: System :: Software Distribution
Requires-Python: >=3.9
Requires-Dist: httpx<1.0,>=0.24
Requires-Dist: keyring<26.0,>=24.0
Requires-Dist: pathspec<1.0,>=0.11
Requires-Dist: python-dotenv<2.0,>=1.0.0
Requires-Dist: pyyaml<7.0,>=6.0
Requires-Dist: questionary<3.0,>=2.0
Requires-Dist: rich<14.0,>=13.0
Requires-Dist: runtm-shared>=0.2.2
Requires-Dist: typer<1.0,>=0.9.0
Provides-Extra: dev
Requires-Dist: mypy<2.0,>=1.0; extra == 'dev'
Requires-Dist: pytest-cov<6.0,>=4.0; extra == 'dev'
Requires-Dist: pytest<9.0,>=7.0; extra == 'dev'
Requires-Dist: ruff>=0.1.0; extra == 'dev'
Requires-Dist: runtm-agents>=0.1.0; extra == 'dev'
Requires-Dist: runtm-sandbox>=0.1.0; extra == 'dev'
Provides-Extra: sandbox
Requires-Dist: runtm-agents>=0.1.0; extra == 'sandbox'
Requires-Dist: runtm-sandbox>=0.1.0; extra == 'sandbox'
